LICENSE
MANIFEST.in
README.md
pyproject.toml
setup.py
ttslearn/__init__.py
ttslearn/dsp.py
ttslearn/env.py
ttslearn/logger.py
ttslearn/notebook.py
ttslearn/train_util.py
ttslearn/util.py
ttslearn.egg-info/PKG-INFO
ttslearn.egg-info/SOURCES.txt
ttslearn.egg-info/dependency_links.txt
ttslearn.egg-info/requires.txt
ttslearn.egg-info/top_level.txt
ttslearn/_example_data/BASIC5000_0001.lab
ttslearn/_example_data/BASIC5000_0001.wav
ttslearn/_example_data/BASIC5000_0001_mono.lab
ttslearn/_example_data/README.md
ttslearn/_example_data/qst1.hed
ttslearn/contrib/__init__.py
ttslearn/contrib/multispk_tacotron2.py
ttslearn/contrib/multispk_util.py
ttslearn/contrib/tacotron2_pwg.py
ttslearn/dnntts/__init__.py
ttslearn/dnntts/gen.py
ttslearn/dnntts/model.py
ttslearn/dnntts/multistream.py
ttslearn/dnntts/tts.py
ttslearn/pretrained/__init__.py
ttslearn/tacotron/__init__.py
ttslearn/tacotron/attention.py
ttslearn/tacotron/decoder.py
ttslearn/tacotron/encoder.py
ttslearn/tacotron/gen.py
ttslearn/tacotron/postnet.py
ttslearn/tacotron/tacotron2.py
ttslearn/tacotron/tts.py
ttslearn/tacotron/frontend/__init__.py
ttslearn/tacotron/frontend/openjtalk.py
ttslearn/tacotron/frontend/text.py
ttslearn/wavenet/__init__.py
ttslearn/wavenet/conv.py
ttslearn/wavenet/gen.py
ttslearn/wavenet/modules.py
ttslearn/wavenet/tts.py
ttslearn/wavenet/upsample.py
ttslearn/wavenet/wavenet.py